{"name":"data-society_student-alcohol-consumption","title":"Student Alcohol Consumption","description":"Secondary school student alcohol consumption data with social, gender and study information.\n\nThe data were obtained in a survey of students math and portuguese language courses in secondary school. It contains a lot of interesting social, gender and study information about students. You can use it for some EDA or try to predict students final grade.\n\nAttributes for both student-mat.csv (Math course) and student-por.csv (Portuguese language course) datasets:\n\nschool - student's school (binary: 'GP' - Gabriel Pereira or 'MS' - Mousinho da Silveira)\n\nsex - student's sex (binary: 'F' - female or 'M' - male)\n\nage - student's age (numeric: from 15 to 22)\n\naddress - student's home address type (binary: 'U' - urban or 'R' - rural)\n\nfamsize - family size (binary: 'LE3' - less or equal to 3 or 'GT3' - greater than 3)\n\nPstatus - parent's cohabitation status (binary: 'T' - living together or 'A' - apart)\n\nMedu - mother's education (numeric: 0 - none, 1 - primary education (4th grade), 2 – 5th to 9th grade, 3 – secondary education or 4 – higher education)\n\nFedu - father's education (numeric: 0 - none, 1 - primary education (4th grade), 2 – 5th to 9th grade, 3 – secondary education or 4 – higher education)\n\nMjob - mother's job (nominal: 'teacher', 'health' care related, civil 'services' (e.g. administrative or police), 'at_home' or 'other')\n\nFjob - father's job (nominal: 'teacher', 'health' care related, civil 'services' (e.g. administrative or police), 'at_home' or 'other')\n\nreason - reason to choose this school (nominal: close to 'home', school 'reputation', 'course' preference or 'other')\n\nguardian - student's guardian (nominal: 'mother', 'father' or 'other')\n\ntraveltime - home to school travel time (numeric: 1 - <15 min., 2 - 15 to 30 min., 3 - 30 min. to 1 hour, or 4 - >1 hour)\n\nstudytime - weekly study time (numeric: 1 - <2 hours, 2 - 2 to 5 hours, 3 - 5 to 10 hours, or 4 - >10 hours)\n\nfailures - number of past class failures (numeric: n if 1<=n<3, else 4)\n\nschoolsup - extra educational support (binary: yes or no)\n\nfamsup - family educational support (binary: yes or no)\n\npaid - extra paid classes within the course subject (Math or Portuguese) (binary: yes or no)\n\nactivities - extra-curricular activities (binary: yes or no)\n\nnursery - attended nursery school (binary: yes or no)\n\nhigher - wants to take higher education (binary: yes or no)\n\ninternet - Internet access at home (binary: yes or no)\n\nromantic - with a romantic relationship (binary: yes or no)\n\nfamrel - quality of family relationships (numeric: from 1 - very bad to 5 - excellent)\n\nfreetime - free time after school (numeric: from 1 - very low to 5 - very high)\n\ngoout - going out with friends (numeric: from 1 - very low to 5 - very high)\n\nDalc - workday alcohol consumption (numeric: from 1 - very low to 5 - very high)\n\nWalc - weekend alcohol consumption (numeric: from 1 - very low to 5 - very high)\n\nhealth - current health status (numeric: from 1 - very bad to 5 - very good)\n\nabsences - number of school absences (numeric: from 0 to 93)\n\nThese grades are related with the course subject, Math or Portuguese:\n\nG1 - first period grade (numeric: from 0 to 20)\n\nG2 - second period grade (numeric: from 0 to 20)\n\nG3 - final grade (numeric: from 0 to 20, output target)\n\nAdditional note: there are several (382) students that belong to both datasets . These students can be identified by searching for identical attributes that characterize each student, as shown in the annexed R file.\n\nSource: Kaggle\n\nhttps://www.kaggle.com/uciml/student-alcohol-consumption","homepage":"https://data.world/data-society/student-alcohol-consumption","resources":[{"name":"student_mat","schema":{"fields":[{"name":"school","title":"school","type":"string","rdfType":"http://www.w3.org/2001/XMLSchema#string","dwSourceId":"school"},{"name":"sex","title":"sex","type":"string","rdfType":"http://www.w3.org/2001/XMLSchema#string","dwSourceId":"sex"},{"name":"age","title":"age","type":"integer","rdfType":"http://www.w3.org/2001/XMLSchema#integer","dwSourceId":"age"},{"name":"address","title":"address","type":"string","rdfType":"http://www.w3.org/2001/XMLSchema#string","dwSourceId":"address"},{"name":"famsize","title":"famsize","type":"string","rdfType":"http://www.w3.org/2001/XMLSchema#string","dwSourceId":"famsize"},{"name":"pstatus","title":"Pstatus","type":"string","rdfType":"http://www.w3.org/2001/XMLSchema#string","dwSourceId":"pstatus"},{"name":"medu","title":"Medu","type":"integer","rdfType":"http://www.w3.org/2001/XMLSchema#integer","dwSourceId":"medu"},{"name":"fedu","title":"Fedu","type":"integer","rdfType":"http://www.w3.org/2001/XMLSchema#integer","dwSourceId":"fedu"},{"name":"mjob","title":"Mjob","type":"string","rdfType":"http://www.w3.org/2001/XMLSchema#string","dwSourceId":"mjob"},{"name":"fjob","title":"Fjob","type":"string","rdfType":"http://www.w3.org/2001/XMLSchema#string","dwSourceId":"fjob"},{"name":"reason","title":"reason","type":"string","rdfType":"http://www.w3.org/2001/XMLSchema#string","dwSourceId":"reason"},{"name":"guardian","title":"guardian","type":"string","rdfType":"http://www.w3.org/2001/XMLSchema#string","dwSourceId":"guardian"},{"name":"traveltime","title":"traveltime","type":"integer","rdfType":"http://www.w3.org/2001/XMLSchema#integer","dwSourceId":"traveltime"},{"name":"studytime","title":"studytime","type":"integer","rdfType":"http://www.w3.org/2001/XMLSchema#integer","dwSourceId":"studytime"},{"name":"failures","title":"failures","type":"integer","rdfType":"http://www.w3.org/2001/XMLSchema#integer","dwSourceId":"failures"},{"name":"schoolsup","title":"schoolsup","type":"boolean","rdfType":"http://www.w3.org/2001/XMLSchema#boolean","dwSourceId":"schoolsup"},{"name":"famsup","title":"famsup","type":"boolean","rdfType":"http://www.w3.org/2001/XMLSchema#boolean","dwSourceId":"famsup"},{"name":"paid","title":"paid","type":"boolean","rdfType":"http://www.w3.org/2001/XMLSchema#boolean","dwSourceId":"paid"},{"name":"activities","title":"activities","type":"boolean","rdfType":"http://www.w3.org/2001/XMLSchema#boolean","dwSourceId":"activities"},{"name":"nursery","title":"nursery","type":"boolean","rdfType":"http://www.w3.org/2001/XMLSchema#boolean","dwSourceId":"nursery"},{"name":"higher","title":"higher","type":"boolean","rdfType":"http://www.w3.org/2001/XMLSchema#boolean","dwSourceId":"higher"},{"name":"internet","title":"internet","type":"boolean","rdfType":"http://www.w3.org/2001/XMLSchema#boolean","dwSourceId":"internet"},{"name":"romantic","title":"romantic","type":"boolean","rdfType":"http://www.w3.org/2001/XMLSchema#boolean","dwSourceId":"romantic"},{"name":"famrel","title":"famrel","type":"integer","rdfType":"http://www.w3.org/2001/XMLSchema#integer","dwSourceId":"famrel"},{"name":"freetime","title":"freetime","type":"integer","rdfType":"http://www.w3.org/2001/XMLSchema#integer","dwSourceId":"freetime"},{"name":"goout","title":"goout","type":"integer","rdfType":"http://www.w3.org/2001/XMLSchema#integer","dwSourceId":"goout"},{"name":"dalc","title":"Dalc","type":"integer","rdfType":"http://www.w3.org/2001/XMLSchema#integer","dwSourceId":"dalc"},{"name":"walc","title":"Walc","type":"integer","rdfType":"http://www.w3.org/2001/XMLSchema#integer","dwSourceId":"walc"},{"name":"health","title":"health","type":"integer","rdfType":"http://www.w3.org/2001/XMLSchema#integer","dwSourceId":"health"},{"name":"absences","title":"absences","type":"integer","rdfType":"http://www.w3.org/2001/XMLSchema#integer","dwSourceId":"absences"},{"name":"g1","title":"G1","type":"integer","rdfType":"http://www.w3.org/2001/XMLSchema#integer","dwSourceId":"g1"},{"name":"g2","title":"G2","type":"integer","rdfType":"http://www.w3.org/2001/XMLSchema#integer","dwSourceId":"g2"},{"name":"g3","title":"G3","type":"integer","rdfType":"http://www.w3.org/2001/XMLSchema#integer","dwSourceId":"g3"}]},"path":"data/student_mat.csv","format":"csv"},{"name":"student_por","schema":{"fields":[{"name":"school","title":"school","type":"string","rdfType":"http://www.w3.org/2001/XMLSchema#string","dwSourceId":"school"},{"name":"sex","title":"sex","type":"string","rdfType":"http://www.w3.org/2001/XMLSchema#string","dwSourceId":"sex"},{"name":"age","title":"age","type":"integer","rdfType":"http://www.w3.org/2001/XMLSchema#integer","dwSourceId":"age"},{"name":"address","title":"address","type":"string","rdfType":"http://www.w3.org/2001/XMLSchema#string","dwSourceId":"address"},{"name":"famsize","title":"famsize","type":"string","rdfType":"http://www.w3.org/2001/XMLSchema#string","dwSourceId":"famsize"},{"name":"pstatus","title":"Pstatus","type":"string","rdfType":"http://www.w3.org/2001/XMLSchema#string","dwSourceId":"pstatus"},{"name":"medu","title":"Medu","type":"integer","rdfType":"http://www.w3.org/2001/XMLSchema#integer","dwSourceId":"medu"},{"name":"fedu","title":"Fedu","type":"integer","rdfType":"http://www.w3.org/2001/XMLSchema#integer","dwSourceId":"fedu"},{"name":"mjob","title":"Mjob","type":"string","rdfType":"http://www.w3.org/2001/XMLSchema#string","dwSourceId":"mjob"},{"name":"fjob","title":"Fjob","type":"string","rdfType":"http://www.w3.org/2001/XMLSchema#string","dwSourceId":"fjob"},{"name":"reason","title":"reason","type":"string","rdfType":"http://www.w3.org/2001/XMLSchema#string","dwSourceId":"reason"},{"name":"guardian","title":"guardian","type":"string","rdfType":"http://www.w3.org/2001/XMLSchema#string","dwSourceId":"guardian"},{"name":"traveltime","title":"traveltime","type":"integer","rdfType":"http://www.w3.org/2001/XMLSchema#integer","dwSourceId":"traveltime"},{"name":"studytime","title":"studytime","type":"integer","rdfType":"http://www.w3.org/2001/XMLSchema#integer","dwSourceId":"studytime"},{"name":"failures","title":"failures","type":"integer","rdfType":"http://www.w3.org/2001/XMLSchema#integer","dwSourceId":"failures"},{"name":"schoolsup","title":"schoolsup","type":"boolean","rdfType":"http://www.w3.org/2001/XMLSchema#boolean","dwSourceId":"schoolsup"},{"name":"famsup","title":"famsup","type":"boolean","rdfType":"http://www.w3.org/2001/XMLSchema#boolean","dwSourceId":"famsup"},{"name":"paid","title":"paid","type":"boolean","rdfType":"http://www.w3.org/2001/XMLSchema#boolean","dwSourceId":"paid"},{"name":"activities","title":"activities","type":"boolean","rdfType":"http://www.w3.org/2001/XMLSchema#boolean","dwSourceId":"activities"},{"name":"nursery","title":"nursery","type":"boolean","rdfType":"http://www.w3.org/2001/XMLSchema#boolean","dwSourceId":"nursery"},{"name":"higher","title":"higher","type":"boolean","rdfType":"http://www.w3.org/2001/XMLSchema#boolean","dwSourceId":"higher"},{"name":"internet","title":"internet","type":"boolean","rdfType":"http://www.w3.org/2001/XMLSchema#boolean","dwSourceId":"internet"},{"name":"romantic","title":"romantic","type":"boolean","rdfType":"http://www.w3.org/2001/XMLSchema#boolean","dwSourceId":"romantic"},{"name":"famrel","title":"famrel","type":"integer","rdfType":"http://www.w3.org/2001/XMLSchema#integer","dwSourceId":"famrel"},{"name":"freetime","title":"freetime","type":"integer","rdfType":"http://www.w3.org/2001/XMLSchema#integer","dwSourceId":"freetime"},{"name":"goout","title":"goout","type":"integer","rdfType":"http://www.w3.org/2001/XMLSchema#integer","dwSourceId":"goout"},{"name":"dalc","title":"Dalc","type":"integer","rdfType":"http://www.w3.org/2001/XMLSchema#integer","dwSourceId":"dalc"},{"name":"walc","title":"Walc","type":"integer","rdfType":"http://www.w3.org/2001/XMLSchema#integer","dwSourceId":"walc"},{"name":"health","title":"health","type":"integer","rdfType":"http://www.w3.org/2001/XMLSchema#integer","dwSourceId":"health"},{"name":"absences","title":"absences","type":"integer","rdfType":"http://www.w3.org/2001/XMLSchema#integer","dwSourceId":"absences"},{"name":"g1","title":"G1","type":"integer","rdfType":"http://www.w3.org/2001/XMLSchema#integer","dwSourceId":"g1"},{"name":"g2","title":"G2","type":"integer","rdfType":"http://www.w3.org/2001/XMLSchema#integer","dwSourceId":"g2"},{"name":"g3","title":"G3","type":"integer","rdfType":"http://www.w3.org/2001/XMLSchema#integer","dwSourceId":"g3"}]},"path":"data/student_por.csv","format":"csv"},{"name":"original/student-mat.csv","path":"original/student-mat.csv","format":"csv","mediatype":"text/csv","bytes":41983},{"name":"original/student-merge.R","path":"original/student-merge.R","format":"R","mediatype":"text/x-rsrc","bytes":269},{"name":"original/student-por.csv","path":"original/student-por.csv","format":"csv","mediatype":"text/csv","bytes":68558}],"keywords":["data society","student","education","alcohol","classification","regression"]}